pyTransition/__init__.py
pyTransition/transition.py
tests/__init__.py
tests/test_transition.py
pyTransition-0.1.2.dist-info/LICENSE
pyTransition-0.1.2.dist-info/METADATA
pyTransition-0.1.2.dist-info/WHEEL
pyTransition-0.1.2.dist-info/top_level.txt
pyTransition-0.1.2.dist-info/RECORD
