Metadata-Version: 2.1
Name: pyTransition
Version: 0.1.2
Summary: A Python package to interact with the Transition API.
Author: Transition City
Classifier: License :: OSI Approved :: MIT License
Classifier: Operating System :: OS Independent
Classifier: Programming Language :: Python :: 3
Requires-Python: >=3.6
License-File: LICENSE
Requires-Dist: requests
Requires-Dist: requests-mock
